{
  "data": {
    "translations": [
      {
        "translatedText": "# TV | Clear News | Monday 1.9.2025"
      },
      {
        "translatedText": ""
      },
      {
        "translatedText": "Budget negotiations. Thumb drug. Modern circus. Weather."
      },
      {
        "translatedText": ""
      },
      {
        "translatedText": "## Government budget meeting"
      },
      {
        "translatedText": ""
      },
      {
        "translatedText": "First, news about politics."
      },
      {
        "translatedText": ""
      },
      {
        "translatedText": "The government has met to decide on next year's budget."
      },
      {
        "translatedText": ""
      },
      {
        "translatedText": "The government plans to make additional adjustments of approximately one billion euros."
      },
      {
        "translatedText": ""
      },
      {
        "translatedText": "The government had already decided on adjustments of 9 billion euros earlier."
      },
      {
        "translatedText": ""
      },
      {
        "translatedText": "Adjustment means that the government makes savings. The goal is that taxes are not increased."
      },
      {
        "translatedText": ""
      },
      {
        "translatedText": "The governing parties have already reached an agreement on the main points of the budget."
      },
      {
        "translatedText": ""
      },
      {
        "translatedText": "The government has met to decide on next year's budget."
      },
      {
        "translatedText": ""
      },
      {
        "translatedText": "The budget meeting lasts 2 days."
      },
      {
        "translatedText": ""
      },
      {
        "translatedText": "The meeting will also discuss the Finns' fundamentalist views on immigration."
      },
      {
        "translatedText": ""
      },
      {
        "translatedText": "The leadership of the Finns Party has criticized immigrants in TV interviews."
      },
      {
        "translatedText": ""
      },
      {
        "translatedText": "## Thumb drug"
      },
      {
        "translatedText": ""
      },
      {
        "translatedText": "Now the news about drugs."
      },
      {
        "translatedText": ""
      },
      {
        "translatedText": "The use of the drug methamphetamine has increased in Finland."
      },
      {
        "translatedText": ""
      },
      {
        "translatedText": "Authorities say that the use of thumb has increased a lot."
      },
      {
        "translatedText": ""
      },
      {
        "translatedText": "Thumb is a transformation drug. Its official name is *alpha-pvp*. Thumb is a highly addictive drug."
      },
      {
        "translatedText": ""
      },
      {
        "translatedText": "Many people with substance abuse problems are in worse shape than before because of their thumb."
      },
      {
        "translatedText": ""
      },
      {
        "translatedText": "For example, in Helsinki, around 100 thumb patients visit the emergency rooms of HUS healthcare each month."
      },
      {
        "translatedText": ""
      },
      {
        "translatedText": "The use of the drug methamphetamine has increased in Finland."
      },
      {
        "translatedText": ""
      },
      {
        "translatedText": "Interior Minister **Mari Rantanen** says that Finland has failed in combating illegal drugs. Rantanen says that the powers of the police may need to be increased."
      },
      {
        "translatedText": ""
      },
      {
        "translatedText": "## Contemporary circus performance Tempo"
      },
      {
        "translatedText": ""
      },
      {
        "translatedText": "Finally, cultural news."
      },
      {
        "translatedText": ""
      },
      {
        "translatedText": "A new contemporary circus performance has been completed in Finland."
      },
      {
        "translatedText": ""
      },
      {
        "translatedText": "The show was designed by Finnish magician **Kalle Nio**."
      },
      {
        "translatedText": ""
      },
      {
        "translatedText": "The choreographer is Brazilian **Fernando Melo**."
      },
      {
        "translatedText": ""
      },
      {
        "translatedText": "The show is called Tempo. It deals with time."
      },
      {
        "translatedText": ""
      },
      {
        "translatedText": "Melo's choreography shows the performers defying gravity."
      },
      {
        "translatedText": ""
      },
      {
        "translatedText": "The movements are demanding. The performers must not falter. Otherwise, the atmosphere of weightlessness will be broken."
      },
      {
        "translatedText": ""
      },
      {
        "translatedText": "A new contemporary circus performance has been completed in Finland."
      },
      {
        "translatedText": ""
      },
      {
        "translatedText": "The first night of the Tempo performance was at the Helsinki Festival."
      },
      {
        "translatedText": ""
      },
      {
        "translatedText": "Tempo may also be performed abroad."
      },
      {
        "translatedText": ""
      },
      {
        "translatedText": "## Tuesday weather"
      },
      {
        "translatedText": ""
      },
      {
        "translatedText": "Still a weather forecast."
      },
      {
        "translatedText": ""
      },
      {
        "translatedText": "On Tuesday the weather will be breezy, meaning it won't rain. The sun will generally shine."
      },
      {
        "translatedText": ""
      },
      {
        "translatedText": "The temperature is around 20 degrees in the south and also over 15 degrees in the north."
      }
    ]
  }
}
