{
  "data": {
    "translations": [
      {
        "translatedText": "# Clear News | Tuesday 10.2.2026"
      },
      {
        "translatedText": ""
      },
      {
        "translatedText": "Threats from Kela. Negotiations over changes to the machine, the closure of Asko and Sotka. Birth defects. Weather."
      },
      {
        "translatedText": ""
      },
      {
        "translatedText": "## Kela employees are being threatened"
      },
      {
        "translatedText": ""
      },
      {
        "translatedText": "First, some news about working life."
      },
      {
        "translatedText": ""
      },
      {
        "translatedText": "Kela employees face a lot of bad behavior and threats. There are several hundred threatening situations every year."
      },
      {
        "translatedText": ""
      },
      {
        "translatedText": "There are even more different observations about safety."
      },
      {
        "translatedText": ""
      },
      {
        "translatedText": "About half of the threats occur in telephone service. A third occur in customer service at Kela service points."
      },
      {
        "translatedText": ""
      },
      {
        "translatedText": "Employees report every threat. Safety Director **Sami Niinikorpi** says that around 2,000 of these are reported each year."
      },
      {
        "translatedText": ""
      },
      {
        "translatedText": "Kela employees are often threatened, even though calls are recorded and many service points have guards."
      },
      {
        "translatedText": ""
      },
      {
        "translatedText": "Kela will report serious threatening situations to the police. In addition, a change to the regulation is now being considered, whereby the name of the Kela employee will not appear in the support decision."
      },
      {
        "translatedText": ""
      },
      {
        "translatedText": "## Bad economic news"
      },
      {
        "translatedText": ""
      },
      {
        "translatedText": "Then economic news."
      },
      {
        "translatedText": ""
      },
      {
        "translatedText": "Elevator company Kone begins change negotiations."
      },
      {
        "translatedText": ""
      },
      {
        "translatedText": "The negotiations involve 840 people at the Hyvinkää factory and in the company's product development. A maximum of 70 positions will be reduced in Finland."
      },
      {
        "translatedText": ""
      },
      {
        "translatedText": "An increasingly large part of the company's operations is the maintenance of elevators and escalators."
      },
      {
        "translatedText": ""
      },
      {
        "translatedText": "Furniture stores Asko and Sotka closed their doors yesterday after the owner, Indoor Group, filed for bankruptcy."
      },
      {
        "translatedText": ""
      },
      {
        "translatedText": "In bankruptcy, the company's assets are handed over to creditors."
      },
      {
        "translatedText": ""
      },
      {
        "translatedText": "The bankruptcy involves 74 stores and approximately 500 employees."
      },
      {
        "translatedText": ""
      },
      {
        "translatedText": "## Birth defects"
      },
      {
        "translatedText": ""
      },
      {
        "translatedText": "Finally, maternity news."
      },
      {
        "translatedText": ""
      },
      {
        "translatedText": "During childbirth, a woman may suffer injuries. In addition, it may be difficult to hold in urine or have difficulty defecating."
      },
      {
        "translatedText": ""
      },
      {
        "translatedText": "Many Finnish women seek help from neighboring Sweden. The women feel that symptoms are not properly diagnosed in Finland."
      },
      {
        "translatedText": ""
      },
      {
        "translatedText": "**Julia** developed symptoms after the birth of her first child. She went to Sweden to investigate birth defects."
      },
      {
        "translatedText": ""
      },
      {
        "translatedText": "In Sweden, pelvic floor repair surgeries began to become more common 10 years ago."
      },
      {
        "translatedText": ""
      },
      {
        "translatedText": "## Weather"
      },
      {
        "translatedText": ""
      },
      {
        "translatedText": "Still a weather forecast."
      },
      {
        "translatedText": ""
      },
      {
        "translatedText": "There will be some light snow in the south tomorrow."
      },
      {
        "translatedText": ""
      },
      {
        "translatedText": "It will be breezy and partly clear in the north."
      },
      {
        "translatedText": ""
      },
      {
        "translatedText": "The temperature ranges from about 5 degrees in the south to about 20 degrees in the north."
      }
    ]
  }
}
