{
  "data": {
    "translations": [
      {
        "translatedText": "# TV | Clear News | Wednesday 8.1.2026"
      },
      {
        "translatedText": ""
      },
      {
        "translatedText": "Ukraine and Greenland. Appliance repairers. National parks. Weather."
      },
      {
        "translatedText": ""
      },
      {
        "translatedText": "## Ukraine and Greenland"
      },
      {
        "translatedText": ""
      },
      {
        "translatedText": "First, foreign policy."
      },
      {
        "translatedText": ""
      },
      {
        "translatedText": "President Alexander Stubb says that Finland will participate in peacekeeping in Ukraine in one way or another in the future. Stubb said that Finland's role is still open."
      },
      {
        "translatedText": ""
      },
      {
        "translatedText": "The President spoke about the matter at a press conference after yesterday's Ukraine meeting in Paris."
      },
      {
        "translatedText": ""
      },
      {
        "translatedText": "President Stubb also said that Finland supports Denmark in the dispute that has arisen over Greenland."
      },
      {
        "translatedText": ""
      },
      {
        "translatedText": "US President Donald Trump has once again said that he wants Greenland under US control."
      },
      {
        "translatedText": ""
      },
      {
        "translatedText": "Secretary of State Marco Rubio says US goal is to buy Greenland from Denmark"
      },
      {
        "translatedText": ""
      },
      {
        "translatedText": "## Appliance repairers"
      },
      {
        "translatedText": ""
      },
      {
        "translatedText": "Then the topic is repairing household appliances."
      },
      {
        "translatedText": ""
      },
      {
        "translatedText": "There is a shortage of home appliance repairers in Finland. New repairers have not been trained for over 10 years. Many repair shops close when a repairer retires."
      },
      {
        "translatedText": ""
      },
      {
        "translatedText": "However, there is plenty of work for repairmen."
      },
      {
        "translatedText": ""
      },
      {
        "translatedText": "Matti Vähämäki repairs household appliances in Munkkiniemi, Helsinki. He says his phone can ring up to 100 times a day."
      },
      {
        "translatedText": ""
      },
      {
        "translatedText": "The EU also wants more and longer-lasting repairs on household appliances. Repairs save money and reduce waste."
      },
      {
        "translatedText": ""
      },
      {
        "translatedText": "## National Parks"
      },
      {
        "translatedText": ""
      },
      {
        "translatedText": "Then we'll talk about national parks."
      },
      {
        "translatedText": ""
      },
      {
        "translatedText": "Finland's national parks have expanded significantly in recent years."
      },
      {
        "translatedText": ""
      },
      {
        "translatedText": "National parks have grown by a total of about 77 square kilometers this decade. That's the equivalent of more than 10,000 football fields."
      },
      {
        "translatedText": ""
      },
      {
        "translatedText": "For example, a 10-hectare area was annexed to Koli National Park in North Karelia in the autumn."
      },
      {
        "translatedText": ""
      },
      {
        "translatedText": "Similar expansions have been made in almost all national parks."
      },
      {
        "translatedText": ""
      },
      {
        "translatedText": "Finland's national parks are slowly growing."
      },
      {
        "translatedText": ""
      },
      {
        "translatedText": "The state expands parks by purchasing small areas of land from private landowners."
      },
      {
        "translatedText": ""
      },
      {
        "translatedText": "## Thursday's weather"
      },
      {
        "translatedText": ""
      },
      {
        "translatedText": "Still a weather forecast."
      },
      {
        "translatedText": ""
      },
      {
        "translatedText": "The weather will be cloudy in most parts of the country tomorrow, Thursday."
      },
      {
        "translatedText": ""
      },
      {
        "translatedText": "It is also widely clear in the east and north."
      },
      {
        "translatedText": ""
      },
      {
        "translatedText": "It may snow on the west coast."
      }
    ]
  }
}
