{
  "data": {
    "translations": [
      {
        "translatedText": "## ރޭޑިއޯ \\| ސާފު ޚަބަރެއް \\| 18 ނޮވެމްބަރ 2023 ވާ ހޮނިހިރު ދުވަހު"
      },
      {
        "translatedText": ""
      },
      {
        "translatedText": "އިރުމަތީ ބޯޑަރުގެ ހާލަތު. އާދައިގެ ރަޝިޔާ މީހުންނެވެ. މަރްޖާ ކުރުކީ އެވެ."
      },
      {
        "translatedText": ""
      },
      {
        "translatedText": "### އިރުމަތީ ބޯޑަރުގެ ހާލަތު"
      },
      {
        "translatedText": ""
      },
      {
        "translatedText": "![ފިންލޭންޑްގެ އުތުރުގައި އޮންނަ ސަލާ ބޯޑަރ ސްޓޭޝަން. ފޮޓޯ: ޖޫސޯ ސްޓޯރ / ވައިލް](https://images.cdn.yle.fi/image/upload/c_crop,h_3033,w_5392,x_0,y_144/ar_1.7777777777777777,c_fill,g_faces,h_675,w_1200/dpr_1.0/ q_auto:eco/f_auto/fl_lossy/v1700230392/39-1202451655773834805e)"
      },
      {
        "translatedText": ""
      },
      {
        "translatedText": "ފިންލޭންޑުގެ ސަލާމަތަށް ބޭނުންވެއްޖެނަމަ މުޅި އިރުމަތީ ބޯޑަރު ބަންދުކުރެވޭނެއެވެ. މިއީ ޑިފެންސް މިނިސްޓަރު **އަންޓީ ހަކަނޭން** ވިދާޅުވާ ވާހަކައެވެ."
      },
      {
        "translatedText": ""
      },
      {
        "translatedText": "ފިންލޭންޑުން ހޮނިހިރު ދުވަހު ހަތަރު ބޯޑަރު ކްރޮސިންގް ބަންދުކުރީ، ރަޝިޔާއިން ގިނަ އަދަދެއްގެ ހިމާޔަތް ހޯދާ މީހުން ފިންލޭންޑަށް އަމާޒުކުރަން ފެށުމުންނެވެ. ހުކުރު ދުވަހު ރަޝިޔާއިން ފިންލޭންޑަށް 220 ހިމާޔަތް ހޯދާ މީހުން އައިސްފައިވެ އެވެ."
      },
      {
        "translatedText": ""
      },
      {
        "translatedText": "ހާލަތު ގޯސްވެއްޖެ ނަމަ އިރުމަތީގެ ހުރިހާ ބޯޑަރު ހުރަސްތަކެއް ބަންދުކުރާނެ ކަމަށް ޑިފެންސް މިނިސްޓަރު އަންޓީ ހަކާނޭން ވިދާޅުވެއްޖެ އެވެ. ހަކާނޭން ބުނާ ގޮތުގައި ފިންލޭންޑުން ރައްކާތެރިވާން ޖެހެ އެވެ"
      },
      {
        "translatedText": ""
      },
      {
        "translatedText": "ރަޝިޔާއިން ފިންލޭންޑަށް މީހުން ޑައިރެކްޓް ކުރަނީ އެގައުމުން ހަމަނުޖެހުން އުފައްދަން ބޭނުންވާތީ އެވެ. ރަޝިޔާއިން 2015 ވަނަ އަހަރުވެސް އަމަލުކުރީ ހަމަ މިގޮތަށެވެ."
      },
      {
        "translatedText": ""
      },
      {
        "translatedText": "އޮފިޝަލުން ބުނާ ގޮތުގައި ހޮނިހިރު ދުވަހު ރަޝިޔާއިން ވަނީ ހިމާޔަތް ހޯދާ މީހުން އުތުރުގެ ބޯޑަރު ހުރަސްތަކަށް ޑައިވަރޓް ކުރަން ފަށާފައެވެ. އެތަނުގެ ބޯޑަރު ސްޓޭޝަންތައް އަދިވެސް ހުޅުވާފައި ހުރެއެވެ."
      },
      {
        "translatedText": ""
      },
      {
        "translatedText": "### އާދައިގެ ރަޝިޔާ މީހުން"
      },
      {
        "translatedText": ""
      },
      {
        "translatedText": "![2022 ވަނަ އަހަރު މޮސްކޯގައި ސިފައިން ހިނގާލުން.ފޮޓޯ: އެރްކާ މިކޮނޭން / ވައިލް](https://images.cdn.yle.fi/image/upload/c_crop,h_2250,w_4000,x_0,y_620/ar_1.7777777777777777,c_fill,g_faces , h_675,w_1200/dpr_1.0/q_auto:eco/f_auto/fl_lossy/v1652081791/39-9521386278c4035763b)"
      },
      {
        "translatedText": ""
      },
      {
        "translatedText": "ފިންލޭންޑުގެ ގިނަ ބަޔަކު ބުނަނީ ޔޫކްރޭންގައި ހިނގަމުންދާ ހަނގުރާމައިގައި އާންމު ރަޝިޔާ މީހުން ބައިވެރިވާ ކަމަށެވެ. މިއީ އާ ދިރާސާއަކުން ދައްކާ ވާހަކައެވެ."
      },
      {
        "translatedText": ""
      },
      {
        "translatedText": "ފިންލޭންޑުގެ ތިން މީހުންގެ ތެރެއިން ދެ މީހަކު ބުނަނީ އާންމު ރަޝިޔާ މީހުން ޔޫކްރޭނަށް ރަޝިޔާއިން ދިން ހަމަލާއާ ދެކޮޅު ހަދަން ފަށަން ޖެހޭ ކަމަށެވެ."
      },
      {
        "translatedText": ""
      },
      {
        "translatedText": "ގާތްގަނޑަކަށް އެންމެންވެސް ބުނަނީ ރަޝިޔާއަކީ ނުތަނަވަސް އަދި ލަފާނުކުރެވޭ ގައުމެއް ކަމަށެވެ."
      },
      {
        "translatedText": ""
      },
      {
        "translatedText": "### މަރްޖާ ކުރުކީ"
      },
      {
        "translatedText": ""
      },
      {
        "translatedText": "![މަރުޖާ ކުރުކީ ކުންފުންޏަށް ހެދުން އެޅުމުގެ ސިނާއަތުގައި އެވޯޑްތަކެއް ލިބިއްޖެއެވެ. ފޮޓޯ: ޖުއްކާ އުއޮޓިލާ / އޭއޯޕީ](https://images.cdn.yle.fi/image/upload/c_crop,h_2089,w_3715,x_1,y_0/ar_1.7777777777777777,c_fill,g_faces,h_675,w_1200/dpr_1.0/ q_auto:eco/f_auto/fl_lossy/v1700215518/39-120216565573a69289c3)"
      },
      {
        "translatedText": ""
      },
      {
        "translatedText": "ފިންލޭންޑްގެ ހެދުން އުފައްދާ ކުންފުނި މަރްޖާ ކުރުކީ ބަންދުކުރަން ފަށައިފި އެވެ."
      },
      {
        "translatedText": ""
      },
      {
        "translatedText": "މަޝްހޫރު އަދި ގާތްގަނޑަކަށް 50 އަހަރު ވެފައިވާ މަރްޖާ ކުރުކީ ކުންފުނިން މައިގަނޑު ގޮތެއްގައި ހެދީ ސްކާފް އާއި ޓައި އެވެ."
      },
      {
        "translatedText": ""
      },
      {
        "translatedText": "ފާއިތުވި އަހަރުތަކުގައި އެ ކުންފުނިން ވަނީ އޭޝިއާ އަށް ވަރަށް ގިނަ އުފެއްދުންތައް ވިއްކާފައެވެ. އެއީ ޔޫރަޕްގައި އެ ކުންފުންޏަށް އުނދަގޫ ކަމަކަށް ވެފައިވެ އެވެ."
      },
      {
        "translatedText": ""
      },
      {
        "translatedText": "ކޮރޯނާ ދުވަސްވަރަކީ މަރްޖާ ކުރުކީ ކުންފުންޏަށް ލިބުނު ނުބައި ގެއްލުމެކެވެ. އެ ކުންފުނީގެ އުފެއްދުންތަކަކީ ޕާޓީތަކުގައި މަގުބޫލު ހަދިޔާތަކެއް ކަމުގައި ވިޔަސް ކޮރޯނާ ވައިރަސްގެ ސަބަބުން ޕާޓީތައް ނިމުނީ އެވެ."
      },
      {
        "translatedText": ""
      },
      {
        "translatedText": "ފަތުރުވެރިންނަކީ އެ ކުންފުންޏަށް މުހިންމު ކަސްޓަމަރުން ކަމުގައި ވިޔަސް ކޮރޯނާ އިން ވަނީ ފަތުރުވެރިކަން ވެސް ހުއްޓުވާފަ އެވެ."
      },
      {
        "translatedText": ""
      },
      {
        "translatedText": "އެ ކުންފުނީގެ ޑިރެކްޓަރު ވެސް ވިދާޅުވަނީ ފިންލޭންޑްގައި އަގުބޮޑު ހެދުން ވިއްކުމަކީ އުނދަގޫ ކަމެއް ކަމަށެވެ."
      },
      {
        "translatedText": ""
      },
      {
        "translatedText": "### މޫސުން"
      },
      {
        "translatedText": ""
      },
      {
        "translatedText": "![ ފޮޓޯ: ވައިލް](https://images.cdn.yle.fi/image/upload/c_crop,h_1080,w_1919,x_0,y_0/ar_1.77777777777777777,c_fill,g_faces,h_675,w_1200/dpr_1.0/q_auto :eco/f_auto/fl_lossy/v1700323494/39-12028456558e083321cf)"
      },
      {
        "translatedText": ""
      },
      {
        "translatedText": "ހުކުރު ދުވަހު ކުޑަކޮށް ސްނޯ ވެދާނެއެވެ. ހުޅަނގަށް އިތުރު ސްނޯ ވެއްޓިދާނެ އެވެ."
      },
      {
        "translatedText": ""
      },
      {
        "translatedText": "ފިނިހޫނުމިން ހުންނަނީ ޕްލަސް +1 އާއި -10 ޑިގްރީއާ ދެމެދުގެ މިންވަރަކަށެވެ. ލެޕްލޭންޑްގައި ހޫނުމިން ހުންނަނީ -10 އާއި -20 ޑިގްރީއާ ދެމެދުގެ މިންވަރަކަށެވެ."
      }
    ]
  }
}
