{
  "data": {
    "translations": [
      {
        "translatedText": "# TV \\| Clear News \\| Monday 3.2.2025"
      },
      {
        "translatedText": ""
      },
      {
        "translatedText": "Strike. USA. Influenza. Weather."
      },
      {
        "translatedText": ""
      },
      {
        "translatedText": "## Strike"
      },
      {
        "translatedText": ""
      },
      {
        "translatedText": "First, the topic of the strike."
      },
      {
        "translatedText": ""
      },
      {
        "translatedText": "A major strike may begin in Finnish grocery stores next week."
      },
      {
        "translatedText": ""
      },
      {
        "translatedText": "The workers are going to go on strike if the employers don't pay more."
      },
      {
        "translatedText": ""
      },
      {
        "translatedText": "Employees and employers will negotiate wages this week."
      },
      {
        "translatedText": ""
      },
      {
        "translatedText": "A big strike in grocery stores may start next week."
      },
      {
        "translatedText": ""
      },
      {
        "translatedText": "Grocery stores still won't be completely closed if a strike starts. Bosses can do the work so that the stores are open."
      },
      {
        "translatedText": ""
      },
      {
        "translatedText": "Shops may still be open less than usual. However, food will not run out."
      },
      {
        "translatedText": ""
      },
      {
        "translatedText": "If the strike starts, it will start next Monday and end on Thursday."
      },
      {
        "translatedText": ""
      },
      {
        "translatedText": "## USA"
      },
      {
        "translatedText": ""
      },
      {
        "translatedText": "Then the topic is the USA."
      },
      {
        "translatedText": ""
      },
      {
        "translatedText": "US President **Donald Trump** has imposed heavy tariffs on three countries. The countries are Canada, Mexico and China."
      },
      {
        "translatedText": ""
      },
      {
        "translatedText": "Canadian and Mexican companies must pay a 25 percent tariff when they sell goods to the US."
      },
      {
        "translatedText": ""
      },
      {
        "translatedText": "For example, when they sell goods to the USA that cost $100, the customs fee is $25."
      },
      {
        "translatedText": ""
      },
      {
        "translatedText": "Canada, Mexico and China are planning to retaliate against the US. They are imposing tariffs on US companies."
      },
      {
        "translatedText": ""
      },
      {
        "translatedText": "President Donald Trump also plans to impose tariffs on European and Finnish companies."
      },
      {
        "translatedText": ""
      },
      {
        "translatedText": "That could be bad for the Finnish economy."
      },
      {
        "translatedText": ""
      },
      {
        "translatedText": "When countries impose high tariffs, they do less trade."
      },
      {
        "translatedText": ""
      },
      {
        "translatedText": "Scientists say that's bad for the world economy."
      },
      {
        "translatedText": ""
      },
      {
        "translatedText": "## Influenza"
      },
      {
        "translatedText": ""
      },
      {
        "translatedText": "Then the topic of influenza."
      },
      {
        "translatedText": ""
      },
      {
        "translatedText": "There is a lot of influenza in Finland right now. Influenza infections have increased recently."
      },
      {
        "translatedText": ""
      },
      {
        "translatedText": "People call health centers a lot because they suspect they have the flu."
      },
      {
        "translatedText": ""
      },
      {
        "translatedText": "There is now influenza throughout Finland."
      },
      {
        "translatedText": ""
      },
      {
        "translatedText": "It is a good idea for older and sick people to get the flu vaccine."
      },
      {
        "translatedText": ""
      },
      {
        "translatedText": "## Weather"
      },
      {
        "translatedText": ""
      },
      {
        "translatedText": "Still a weather forecast."
      },
      {
        "translatedText": ""
      },
      {
        "translatedText": "It won't rain much during the day on Tuesday."
      },
      {
        "translatedText": ""
      },
      {
        "translatedText": "Snow will come to Finland from the west in the evening. The whole country will be freezing on Tuesday."
      },
      {
        "translatedText": ""
      }
    ]
  }
}
