{
  "data": {
    "translations": [
      {
        "translatedText": "## Radio \\| Skaidras ziņas \\| Piektdiena, 24.11.2023"
      },
      {
        "translatedText": ""
      },
      {
        "translatedText": "Situācija uz austrumu robežas. Izraēlas un Hamas pamiers. Izlikšana. Laikapstākļi."
      },
      {
        "translatedText": ""
      },
      {
        "translatedText": "### Austrumu robežas situācija"
      },
      {
        "translatedText": ""
      },
      {
        "translatedText": "![Cilvēki dienas laikā ieradās Raja-Joosep robežstacijā Inari pilsētā. Foto: Juuso Stoor / Yle](https://images.cdn.yle.fi/image/upload/c_crop,h_3368,w_5986,x_0,y_0/ar_1.7777777777777777,c_fill,g_faces,h_6270,0/d_1275,0 q_auto:eco/f_auto/fl_lossy/v1700827102/39-120618465608fd4818b7)"
      },
      {
        "translatedText": ""
      },
      {
        "translatedText": "Uz Somijas un Krievijas robežas piektdiena bija mierīga."
      },
      {
        "translatedText": ""
      },
      {
        "translatedText": "No Krievijas uz Raja-Joosep robežstaciju Inari ieradās trīs cilvēki. Tie bija jemenieši."
      },
      {
        "translatedText": ""
      },
      {
        "translatedText": "Raja-Jooseppi atrodas tālu ziemeļos. Tagad tā ir vienīgā atvērtā robežšķērsošanas vieta uz austrumu robežas."
      },
      {
        "translatedText": ""
      },
      {
        "translatedText": "Somija ir slēgusi citus robežšķērsošanas punktus. Tie ir slēgti vismaz līdz Ziemassvētkiem."
      },
      {
        "translatedText": ""
      },
      {
        "translatedText": "Iemesls tam, ka Krievija arvien vairāk migrantu virzījusi uz Somiju."
      },
      {
        "translatedText": ""
      },
      {
        "translatedText": "### Izraēlas un Hamas pamiers"
      },
      {
        "translatedText": ""
      },
      {
        "translatedText": "![Pamiera laikā Gazai tiks nosūtīta palīdzība. Fotoattēls: Thomas Samson / AFP](https://images.cdn.yle.fi/image/upload/c_crop,h_2879,w_5119,x_0,y_533/ar_1.777777777777777,c_fill,g_faces,h_675,w/dpr1_2 q_auto:eco/f_auto/fl_lossy/v1700822253/39-120580865603d3467a7a)"
      },
      {
        "translatedText": ""
      },
      {
        "translatedText": "Tuvajos Austrumos Gazā sācies pamiers starp Izraēlu un teroristu organizāciju Hamas. Tas prasīs vismaz četras dienas. Pamiera laikā Izraēla un Hamas nekaro."
      },
      {
        "translatedText": ""
      },
      {
        "translatedText": "Pārtraukuma laikā Izraēla atļauj kravas automašīnām uz Gazu vest, piemēram, medikamentus, pārtiku un benzīnu."
      },
      {
        "translatedText": ""
      },
      {
        "translatedText": "Pamiera laikā Izraēla atbrīvo palestīniešu ieslodzītos, bet Hamas atbrīvo izraēliešus."
      },
      {
        "translatedText": ""
      },
      {
        "translatedText": "Gazas karš sākās oktobra sākumā, kad Hamas uzbruka Izraēlai. Kopš tā laika Izraēla ir bombardējusi Gazu. Cilvēku situācija Gazā ir patiešām slikta."
      },
      {
        "translatedText": ""
      },
      {
        "translatedText": "### Izlikšana"
      },
      {
        "translatedText": ""
      },
      {
        "translatedText": "![Īrnieka izlikšana ir sarežģīta. Foto: Oļegs Elkovs / Alamy/All Over Press](https://images.cdn.yle.fi/image/upload/c_crop,h_3182,w_5657,x_121,y_740/ar_1.7777777777777777,c_fill_,g_25,/1 dpr_1.0/q_auto:eco/f_auto/fl_lossy/v1698135288/39-115380264d2449083906)"
      },
      {
        "translatedText": ""
      },
      {
        "translatedText": "Lielākā daļa somu uzskata, ka izlikt īrnieku no dzīvokļa ir pārāk grūti. Tā teikts jaunā aptaujā."
      },
      {
        "translatedText": ""
      },
      {
        "translatedText": "Lai īrnieku izliktu, nepieciešams tiesas lēmums. Tikai iestāde var veikt izlikšanu. Likums sniedz īrniekam lielu aizsardzību."
      },
      {
        "translatedText": ""
      },
      {
        "translatedText": "Dzīvokļa īpašniekam ir sarežģīta situācija, ja, piemēram, īrnieks nemaksā īri."
      },
      {
        "translatedText": ""
      },
      {
        "translatedText": "Vairāk nekā 80 procenti somu uzskata, ka šodien izlikšana ir pārāk sarežģīta."
      },
      {
        "translatedText": ""
      },
      {
        "translatedText": "### Sāmi"
      },
      {
        "translatedText": ""
      },
      {
        "translatedText": "![Vīrietis pagājušā gada aprīlī vicināja sāmu karogu pie parlamenta ēkas. Foto: Linda Tammela / Yle](https://images.cdn.yle.fi/image/upload/c_crop,h_659,w_1173,x_0,y_133/ar_1.777777777777777,c_fill,g_faces,h_675,/d_pr1_200,/. q_auto:eco/f_auto/fl_lossy/v1693572536/39-10986686437da2797694)"
      },
      {
        "translatedText": ""
      },
      {
        "translatedText": "Somijā sāmu diskriminācija tiek pētīta mūsdienās un pagātnē. Patiesības komisija šo lietu izmeklē."
      },
      {
        "translatedText": ""
      },
      {
        "translatedText": "Komisija apkopo sāmu pieredzi par Somijas valsti un varas iestādēm."
      },
      {
        "translatedText": ""
      },
      {
        "translatedText": "Agrāk Somija nepieņēma sāmu tautas kultūru. Viņi gribēja mainīt sāmus, lai tie būtu tādi paši kā citi somi."
      },
      {
        "translatedText": ""
      },
      {
        "translatedText": "Attieksme pret sāmiem izraisīja daudz bēdu. Sāmi ir Somijas pamatiedzīvotāji."
      },
      {
        "translatedText": ""
      },
      {
        "translatedText": "### Laikapstākļi"
      },
      {
        "translatedText": ""
      },
      {
        "translatedText": "![ Foto: Yle](https://images.cdn.yle.fi/image/upload/c_crop,h_1080,w_1919,x_0,y_0/ar_1.7777777777777777,c_fill,g_faces,h_675/d_prq_120. :eco/f_auto/fl_lossy/v1700835658/39-12063856560b12785459)"
      },
      {
        "translatedText": ""
      },
      {
        "translatedText": "Sestdien pa dienu rietumkrastā un ziemeļos nedaudz snigs."
      },
      {
        "translatedText": ""
      },
      {
        "translatedText": "Gaisa temperatūra ir no -1 grāda līdz -10 grādiem. Siltākais ir ziemeļos."
      }
    ]
  }
}
