{
  "data": {
    "translations": [
      {
        "translatedText": "## Радіо \\| Очистити новини \\| у суботу, 4 листопада 2023 р"
      },
      {
        "translatedText": ""
      },
      {
        "translatedText": "податки. Землетрус у Непалі. Україна. Газа. День всіх святих. Прогноз."
      },
      {
        "translatedText": ""
      },
      {
        "translatedText": "### Задоволеність оподаткуванням"
      },
      {
        "translatedText": ""
      },
      {
        "translatedText": "![Фіни із задоволенням платять податки. Фото: Henrietta Hassinen / Yle](https://images.cdn.yle.fi/image/upload/c_crop,h_3061,w_5443,x_0,y_226/ar_1.777777777777777,c_fill,g_faces,h_675,w_1200/dpr_1.0/ q_auto:eco/f_auto/fl_lossy/v1692510416/39-115736664dc9b0569c81)"
      },
      {
        "translatedText": ""
      },
      {
        "translatedText": "Більшість фінів задоволені оподаткуванням. Податкова адміністрація запитала у фінів, що вони думають про сплату податків."
      },
      {
        "translatedText": ""
      },
      {
        "translatedText": "Понад 70 відсотків фінів із задоволенням платять податки."
      },
      {
        "translatedText": ""
      },
      {
        "translatedText": "Лише 17 відсотків фінів кажуть, що їм не подобається платити податки. Однак більшість з них вважає, що податки все ж потрібно платити."
      },
      {
        "translatedText": ""
      },
      {
        "translatedText": "Задоволеність сплатою податків явно зросла за останні 10 років."
      },
      {
        "translatedText": ""
      },
      {
        "translatedText": "### Землетрус у Непалі"
      },
      {
        "translatedText": ""
      },
      {
        "translatedText": "![Зруйновані будинки в Джаджаркот, Непал. Фото: Балкумар Шарма / AFP](https://images.cdn.yle.fi/image/upload/c_crop,h_1350,w_2400,x_0,y_51/ar_1.777777777777777,c_fill,g_faces,h_675,w_1200/dpr_1.0/ q_auto:eco/f_auto/fl_lossy/v1699091137/39-1195827654612690580a)"
      },
      {
        "translatedText": ""
      },
      {
        "translatedText": "У Непалі стався потужний землетрус. Землетрус стався на заході Непалу в п'ятницю ввечері."
      },
      {
        "translatedText": ""
      },
      {
        "translatedText": "В результаті землетрусу загинули щонайменше 150 людей. Кількість загиблих може зрости, коли з місця буде отримано більше інформації. Багато людей також постраждали під час землетрусу в Непалі. Під час землетрусу зруйнувалося багато будівель."
      },
      {
        "translatedText": ""
      },
      {
        "translatedText": "Землетрус у Непалі стався у віддаленому районі. Тому інформація про руйнування надходить повільно."
      },
      {
        "translatedText": ""
      },
      {
        "translatedText": "### Візит президента ЄС в Україну"
      },
      {
        "translatedText": ""
      },
      {
        "translatedText": "![Урсула фон дер Ляєн зустрілася з президентом Володимиром Зеленським на київському вокзалі. Фото: AFP](https://images.cdn.yle.fi/image/upload/c_crop,h_1687,w_3000,x_0,y_305/ar_1.7777777777777777,c_fill,g_faces,h_675,w_1200/dpr_1.0/q_auto:eco /f_auto/fl_lossy/v1699098434/39-119583265462e51258c1)"
      },
      {
        "translatedText": ""
      },
      {
        "translatedText": "Президент Єврокомісії **Урсула фон дер Ляєн** відвідала Україну в суботу. У Києві фон дер Ляєн зустрілася з президентом України **Володимиром Зеленським**."
      },
      {
        "translatedText": ""
      },
      {
        "translatedText": "Фон дер Ляєн говорила в Україні, наприклад, про те, як Україна може колись стати членом ЄС."
      },
      {
        "translatedText": ""
      },
      {
        "translatedText": "Фон дер Ляєн також розповіла про підтримку України з боку ЄС."
      },
      {
        "translatedText": ""
      },
      {
        "translatedText": "### Ситуація в Газі"
      },
      {
        "translatedText": ""
      },
      {
        "translatedText": "![Ізраїль зосередив військові удари по північній частині Гази. Фото: Ilkka Kemppinen / Yle](https://images.cdn.yle.fi/image/upload/c_crop,h_1121,w_1994,x_5,y_0/ar_1.7777777777777777,c_fill,g_faces,h_675,w_1200/dpr_1.0/ q_auto:eco/f_auto/fl_lossy/v1699023208/39-1195711654506b2bc2d4)"
      },
      {
        "translatedText": ""
      },
      {
        "translatedText": "Близько мільйона людей переїхали з Гази в південну частину території через війну."
      },
      {
        "translatedText": ""
      },
      {
        "translatedText": "Експерти кажуть, що принаймні 800 000 людей увійшли в зону, але ця цифра може сягати мільйона. Про це говорить спеціальний представник США з питань гуманітарної допомоги на Близькому Сході."
      },
      {
        "translatedText": ""
      },
      {
        "translatedText": "Удари ізраїльської авіації та сухопутних сил зосереджені на півночі Гази. Тому люди втекли на південь. На півночі Гази все ще перебуває близько 400 тисяч людей."
      },
      {
        "translatedText": ""
      },
      {
        "translatedText": "### День всіх святих"
      },
      {
        "translatedText": ""
      },
      {
        "translatedText": "![На святий день несуть свічки на могили. Фото: Leena-kaisa Laakso / Yle](https://images.cdn.yle.fi/image/upload/c_crop,h_2268,w_4032,x_0,y_435/ar_1.7777777777777777,c_fill,g_faces,h_675,w_1200/dpr_1. 0/q_auto:eco/f_auto/fl_lossy/v1699101771/39-119586665463c1d71d1c)"
      },
      {
        "translatedText": ""
      },
      {
        "translatedText": "Сьогодні в суботу День всіх святих. День всіх святих є важливим у християнській традиції. Це день пам'яті святих, мучеників і померлих."
      },
      {
        "translatedText": ""
      },
      {
        "translatedText": "У День всіх святих ми згадуємо близьких людей, які вже померли. У День всіх святих свічки несуть на могили близьких. Храми згадують тих парафіян, які померли з минулого дня Всіх Святих."
      },
      {
        "translatedText": ""
      },
      {
        "translatedText": "День всіх святих у Фінляндії завжди відзначається в першу суботу листопада."
      },
      {
        "translatedText": ""
      },
      {
        "translatedText": "### Погода"
      },
      {
        "translatedText": ""
      },
      {
        "translatedText": "![У неділю переважно хмарно.](https://images.cdn.yle.fi/image/upload/c_crop,h_1080,w_1919,x_0,y_0/ar_1.7777777777777777,c_fill,g_faces,h_675,w_1200/dpr_1.0 /q_auto:eco/f_auto/fl_lossy/v1699111715/39-1195891654662ff4432c)"
      },
      {
        "translatedText": ""
      },
      {
        "translatedText": "Погода переважно хмарна, дощова. На південному заході Фінляндії сонце іноді може світити трохи. Температура переважно від 3 до 8 градусів тепла. На півночі Фінляндії холодніше."
      }
    ]
  }
}
