{
  "data": {
    "translations": [
      {
        "translatedText": "Радио Selkouutiset Понедельник, 27 ноября 2023 г."
      },
      {
        "translatedText": "---------------------------------------"
      },
      {
        "translatedText": ""
      },
      {
        "translatedText": "Офисные здания. Обследование воздуха в детских садах. Кинопремия. Погода."
      },
      {
        "translatedText": ""
      },
      {
        "translatedText": "### Офисные здания"
      },
      {
        "translatedText": ""
      },
      {
        "translatedText": "![Дом Спонды на улице Маннергейминтие в Хельсинки будет снесен, а на его месте появится новое офисное здание. Фото: Эса Сювакуру / Yle](https://images.cdn.yle.fi/image/upload/c_crop,h_3270,w_5814,x_0,y_404/ar_1.7777777777777777,c_fill,g_faces,h_675,w_1200/dpr_1.0/ q_auto:eco/f_auto/fl_lossy/v1700118894/39-12013716555c1029fb19)"
      },
      {
        "translatedText": ""
      },
      {
        "translatedText": "Компании привлекают сотрудников с удаленной работы обратно в офисы. Компании надеются, что новые или отремонтированные помещения привлекут обратно сотрудников."
      },
      {
        "translatedText": ""
      },
      {
        "translatedText": "На многих рабочих местах существуют планы по укреплению корпоративной культуры, повышению уровня обучения и повышению благосостояния. Все это сложно сделать удаленно или в некачественных помещениях."
      },
      {
        "translatedText": ""
      },
      {
        "translatedText": "Хорошее расположение рабочего места также важно как никогда. Например, в Хельсинки компании заинтересованы в центре города."
      },
      {
        "translatedText": ""
      },
      {
        "translatedText": "В центре Хельсинки даже сносят старое офисное здание и строят на его месте новое. Многие компании готовы платить за хорошее расположение."
      },
      {
        "translatedText": ""
      },
      {
        "translatedText": "### Качество воздуха в детских садах"
      },
      {
        "translatedText": ""
      },
      {
        "translatedText": "![Дети украсили детский сад с очистителем воздуха в Камомилле в Вийкки, Хельсинки. Фото: Мартен Лампен / Yle](https://images.cdn.yle.fi/image/upload/c_crop,h_2250,w_4000,x_0,y_334/ar_1.7777777777777777,c_fill,g_faces,h_675,w_1200/dpr_1.0/ q_auto:eco/f_auto/fl_lossy/v1695638511/39-117653165115d5600150)"
      },
      {
        "translatedText": ""
      },
      {
        "translatedText": "Очистители воздуха в детских садах позволяют существенно снизить заболеваемость детей."
      },
      {
        "translatedText": ""
      },
      {
        "translatedText": "Двухлетнее исследование выясняет, как эффективная очистка воздуха в детском саду влияет на болезни. В ходе исследования также изучаются заболевания персонала. При этом явное влияние оказывает отсутствие на работе родителей детей."
      },
      {
        "translatedText": ""
      },
      {
        "translatedText": "После первого года исследований результаты хорошие. Доктор-исследователь Энни Санмарк говорит, что заболеваемость снизилась примерно на 30 процентов."
      },
      {
        "translatedText": ""
      },
      {
        "translatedText": "1 день отсутствия работника обходится работодателю примерно в 370 евро. Сюда не входят расходы на здравоохранение или цены на лекарства."
      },
      {
        "translatedText": ""
      },
      {
        "translatedText": "Очистители воздуха понравились в исследовательских детских садах. Звук у них разумный. Кроме того, было замечено, что соответствующий шум успокаивает детей, позволяя им отдохнуть и заснуть во время сна."
      },
      {
        "translatedText": ""
      },
      {
        "translatedText": "### Кинорежиссер Суви Уэст"
      },
      {
        "translatedText": ""
      },
      {
        "translatedText": "![Саамский кинорежиссер Суви Уэст. Фото: Линда Таммела / Yle](https://images.cdn.yle.fi/image/upload/c_crop,h_2268,w_4032,x_0,y_120/ar_1.7777777777777777,c_fill,g_faces,h_675,w_1200/dpr_1.0/ q_auto:eco/f_auto/fl_lossy/v1613476645/39-774637602bb23ea1c4a)"
      },
      {
        "translatedText": ""
      },
      {
        "translatedText": "Режиссер Суви Уэст получил награду «Кинорежиссер года». Его предоставила Ассоциация финских кинорежиссеров SELO. Уэст получил награду за фильм «Махкан: Возвращение домой». Фильм о возвращении саамских артефактов."
      },
      {
        "translatedText": ""
      },
      {
        "translatedText": "Мировая премьера фильма состоялась на Международном кинофестивале в Торонто."
      },
      {
        "translatedText": ""
      },
      {
        "translatedText": "В обосновании премии говорится, что Уэст снимает красивые и трогательные фильмы на темы, важные для саамского народа. В то же время они помогают большинству населения Финляндии лучше понять культуру и самобытность коренного населения."
      },
      {
        "translatedText": ""
      },
      {
        "translatedText": "Кинорежиссер года выбирается с 2004 года."
      },
      {
        "translatedText": ""
      },
      {
        "translatedText": "### Погода"
      },
      {
        "translatedText": ""
      },
      {
        "translatedText": "![ Фото: Yle](https://images.cdn.yle.fi/image/upload/c_crop,h_1080,w_1919,x_0,y_0/ar_1.7777777777777777,c_fill,g_faces,h_675,w_1200/dpr_1.0/q_auto :eco/f_auto/fl_lossy/v1701100995/39-12073206564bd79da68c)"
      },
      {
        "translatedText": ""
      },
      {
        "translatedText": "Во вторник почти на всей территории страны выпадет от 3 до 13 сантиметров снега. В Лапландии это путаа, что означает отсутствие дождя."
      },
      {
        "translatedText": ""
      },
      {
        "translatedText": "Температура повысится примерно до 5 градусов ниже нуля по всей стране, но при этом усилится ветер. Особенно дует ветер на севере. Порывы ветра здесь могут достигать 18 метров в секунду."
      },
      {
        "translatedText": ""
      },
      {
        "translatedText": "К среде снегопад переместится в Южную и Центральную Лапландию."
      }
    ]
  }
}
