{
  "data": {
    "translations": [
      {
        "translatedText": "## રેડિયો \\| સ્પષ્ટ સમાચાર \\| બુધવાર 22 નવેમ્બર 2023"
      },
      {
        "translatedText": ""
      },
      {
        "translatedText": "પૂર્વ સરહદ. આશ્રય સીકર્સ. સરકારનો વિશ્વાસ. દારૂ નુકસાન કરે છે. આગાહી."
      },
      {
        "translatedText": ""
      },
      {
        "translatedText": "### પૂર્વ સરહદને મજબૂત બનાવવી"
      },
      {
        "translatedText": ""
      },
      {
        "translatedText": "![પૂર્વીય સરહદને વધુ મજબૂત બનાવવામાં આવી છે, ઉદાહરણ તરીકે, કાંટાળા તાર અવરોધો. ફોટો: Ari Haimakainen / Yle](https://images.cdn.yle.fi/image/upload/c_crop,h_3078,w_5472,x_0,y_157/ar_1.777777777777777,c_fill,g_faces,h_177777777777777777777777777777777777777777777777777777777777777777777777777777777777777777777777777777777777777777777777777777777777777777777777,c_fill,g_faces,h/20p_01/01/05 q_auto:eco/f_auto/fl_lossy/v1700489748/39-1203622655b691ed016a)"
      },
      {
        "translatedText": ""
      },
      {
        "translatedText": "ફિનલેન્ડ અવરોધો સાથે પૂર્વીય સરહદને મજબૂત બનાવે છે. જેનો હેતુ લોકોને રશિયાની પરમિટ વિના ફિનલેન્ડમાં પ્રવેશતા અટકાવવાનો છે."
      },
      {
        "translatedText": ""
      },
      {
        "translatedText": "રશિયાએ લોકોને સરહદ પર લાવ્યા છે, જેને રશિયા ફિનિશ બાજુ મોકલે છે. તેથી જ સરહદ ક્રોસિંગ પર અને તેની નજીક અવરોધો બનાવવામાં આવે છે."
      },
      {
        "translatedText": ""
      },
      {
        "translatedText": "ઓછામાં ઓછા સલ્લા, કુસામો અને વર્ટીયસ બોર્ડર સ્ટેશનની આસપાસ વાડ બાંધવામાં આવી રહી છે."
      },
      {
        "translatedText": ""
      },
      {
        "translatedText": "ફિનલેન્ડ માત્ર સલ્લા અને વર્ટીયસ બોર્ડર સ્ટેશન પર જ પૂર્વીય સરહદ પર આશ્રય શોધનારાઓને સ્વીકારે છે. ફિનલેન્ડે દક્ષિણપૂર્વ ફિનલેન્ડની બોર્ડર ક્રોસિંગ બંધ કરી દીધી છે."
      },
      {
        "translatedText": ""
      },
      {
        "translatedText": "### બોર્ડર ક્રોસિંગ પોઈન્ટ"
      },
      {
        "translatedText": ""
      },
      {
        "translatedText": "![સલ્લા બોર્ડર સ્ટેશન પર બુધવારે આશ્રય શોધનારાઓ. ફોટો: જુસ્સી નુકારી / લેહટીકુવા](https://images.cdn.yle.fi/image/upload/c_crop,h_2879,w_5119,x_0,y_429/ar_1.7777777777777777,c_fill,g_faces/6p_01/20p_0,h. q_auto:eco/f_auto/fl_lossy/v1700655653/39-1204918655df1f3cef50)"
      },
      {
        "translatedText": ""
      },
      {
        "translatedText": "સરકાર બોર્ડર ક્રોસિંગ પર ટ્રાફિકને મર્યાદિત કરવા માટે નવા રસ્તાઓ તૈયાર કરી રહી છે."
      },
      {
        "translatedText": ""
      },
      {
        "translatedText": "મંગળવારે, ન્યાયના નાયબ ચાન્સેલરે સરકાર જે યોજના તૈયાર કરી રહી છે તેનો ઇનકાર કર્યો હતો. યોજના ચાલુ હોવાથી આ યોજનાને જાહેર કરવામાં આવી નથી. આ યોજના ફિનલેન્ડમાં આશ્રય માટે અરજી કરવાની શક્યતાને કદાચ ખૂબ મર્યાદિત કરી દીધી છે."
      },
      {
        "translatedText": ""
      },
      {
        "translatedText": "સરકાર હવે પૂર્વીય સરહદેથી પરમિટ વિના ફિનલેન્ડમાં પ્રવેશતા લોકોને રોકવા માટે એક નવો પ્રસ્તાવ તૈયાર કરી રહી છે."
      },
      {
        "translatedText": ""
      },
      {
        "translatedText": "ફિનલેન્ડે ફ્રન્ટેક્સ, યુરોપિયન બોર્ડર અને કોસ્ટ ગાર્ડ એજન્સીને પણ મદદની વિનંતી કરી છે. ફિનલેન્ડ વિનંતી કરે છે કે પૂર્વીય સરહદ પરની પરિસ્થિતિને કારણે Frontex મદદ માટે 60 અધિકારીઓને ફિનલેન્ડ મોકલે."
      },
      {
        "translatedText": ""
      },
      {
        "translatedText": "![સરકારે સંસદનો વિશ્વાસ મેળવ્યો. ફોટો: સિલ્જા વિતાલા / Yle](https://images.cdn.yle.fi/image/upload/c_crop,h_2241,w_3983,x_0,y_325/ar_1.777777777777777,c_fill,g_faces,h/17_15,h/17_15 q_auto:eco/f_auto/fl_lossy/v1696934704/39-118409465252a7d6dc9d)"
      },
      {
        "translatedText": ""
      },
      {
        "translatedText": "મધ્યવર્તી પ્રશ્ન મતમાં સરકારે સંસદનો વિશ્વાસ હાંસલ કર્યો છે."
      },
      {
        "translatedText": ""
      },
      {
        "translatedText": "વિરોધ પક્ષો એસડીપી, ગ્રીન્સ અને લેફ્ટ એલાયન્સ દ્વારા વચગાળાનો પ્રશ્ન કરવામાં આવ્યો હતો. તેઓ કહે છે કે સરકારના કાપ ઘણા યુવાનો અને વિદ્યાર્થીઓને નિશાન બનાવે છે."
      },
      {
        "translatedText": ""
      },
      {
        "translatedText": "સરકારે 96-76ના મત સાથે સંસદનો વિશ્વાસ પ્રાપ્ત કર્યો. સંસદમાં બહુમતી સરકાર પર વિશ્વાસ કરે છે. તેથી જ સરકાર કામ ચાલુ રાખી શકે છે."
      },
      {
        "translatedText": ""
      },
      {
        "translatedText": "### દારૂના નુકસાન"
      },
      {
        "translatedText": ""
      },
      {
        "translatedText": "![દારૂના નુકસાનથી સમાજને ઘણો ખર્ચ થાય છે. ફોટો: ટીના જુટીલા / Yle](https://images.cdn.yle.fi/image/upload/c_crop,h_2944,w_5235,x_0,y_312/ar_1.777777777777777,c_fill,g_faces,h/17_15,h/17_15 q_auto:eco/f_auto/fl_lossy/v1700406169/39-1203003655a1febe291f)"
      },
      {
        "translatedText": ""
      },
      {
        "translatedText": "આલ્કોહોલના નુકસાનથી ફિનિશ સમાજ માટે ઘણો ખર્ચ થાય છે."
      },
      {
        "translatedText": ""
      },
      {
        "translatedText": "આલ્ટો યુનિવર્સિટીએ દારૂના નુકસાનના ખર્ચનો અભ્યાસ કર્યો છે. આલ્કોહોલના નુકસાનને કારણે ગયા વર્ષે સમાજને ઓછામાં ઓછા 1.4 બિલિયન યુરોનો ખર્ચ થયો હતો. ખર્ચ આલ્કોહોલ સંબંધિત મૃત્યુ, આલ્કોહોલ સંબંધિત રોગોની સારવાર, ગુનાઓ અને અપંગતામાંથી આવે છે."
      },
      {
        "translatedText": ""
      },
      {
        "translatedText": "વધુમાં, એમ્પ્લોયરોએ ગયા વર્ષે આલ્કોહોલને કારણે થતા નુકસાનને કારણે નાણાકીય નુકસાનમાં 500 મિલિયન યુરોનો ખર્ચ કર્યો હતો. એમ્પ્લોયર ખર્ચ કરે છે, ઉદાહરણ તરીકે, જો કર્મચારી કામ કરવામાં અસમર્થ હોય."
      },
      {
        "translatedText": ""
      },
      {
        "translatedText": "### હવામાન"
      },
      {
        "translatedText": ""
      },
      {
        "translatedText": "![હવામાન ઠંડુ થાય છે, તેથી તાપમાન વધે છે.](https://images.cdn.yle.fi/image/upload/c_crop,h_1080,w_1919,x_0,y_0/ar_1.7777777777777777,c_fill,g_faces,h_62050 /dpr_1. 0/q_auto:eco/f_auto/fl_lossy/v1700671048/39-1205140655e2e229bced)"
      },
      {
        "translatedText": ""
      },
      {
        "translatedText": "રાત્રે ખૂબ બરફ પડે છે. પશ્ચિમમાં, કેટલાક સ્થળોએ 20 સેમી સુધી બરફ પડશે. પશ્ચિમમાં રાત્રે બરફ બંધ થઈ જશે. દક્ષિણમાં તાપમાન 0 અને +2 ડિગ્રી વચ્ચે છે. ઉત્તરમાં, મોટે ભાગે -4 અને -7 ડિગ્રી વચ્ચે. સ્થળોએ પવન મજબૂત છે."
      }
    ]
  }
}
