{
  "data": {
    "translations": [
      {
        "translatedText": "# News of the week in plain Finnish | Saturday 20.6.2026"
      },
      {
        "translatedText": ""
      },
      {
        "translatedText": "Food safety"
      },
      {
        "translatedText": ""
      },
      {
        "translatedText": "Listen"
      },
      {
        "translatedText": ""
      },
      {
        "translatedText": "You can read the news simultaneously below."
      },
      {
        "translatedText": ""
      },
      {
        "translatedText": "## Topic of the week"
      },
      {
        "translatedText": ""
      },
      {
        "translatedText": "The topic of the program this time is food safety."
      },
      {
        "translatedText": ""
      },
      {
        "translatedText": "Food safety means that the food in stores is clean and safe to eat."
      },
      {
        "translatedText": ""
      },
      {
        "translatedText": "Health inspectors inspect grocery stores regularly."
      },
      {
        "translatedText": ""
      },
      {
        "translatedText": "Yle requested information about the inspections carried out by health inspectors in 2023-2025."
      },
      {
        "translatedText": ""
      },
      {
        "translatedText": "We will now tell you more about how S Group, K Group and Lidl survived the inspections."
      },
      {
        "translatedText": ""
      },
      {
        "translatedText": "![Close-up of a butcher's hand measuring the temperature of meat with a thermometer. ](https://img.img-cdn.yle.fi/crop_extract,w_8256,h_4644,x_0,y_77/crop_fill,w_767,h_431,ar_16:9,dpr_1/f_auto/39-16589436a2a729c83503/1781167254)"
      },
      {
        "translatedText": ""
      },
      {
        "translatedText": "Open image viewer"
      },
      {
        "translatedText": ""
      },
      {
        "translatedText": "Authorities regularly inspect grocery stores. Here, the temperature of meat is measured at the sales counter. Photo: Johanna Erjonsalo / Yle"
      },
      {
        "translatedText": ""
      },
      {
        "translatedText": "## Lidl and S Group"
      },
      {
        "translatedText": ""
      },
      {
        "translatedText": "Lidl received the best ratings among the retail groups."
      },
      {
        "translatedText": ""
      },
      {
        "translatedText": "There were almost no problems at all in Lidl stores."
      },
      {
        "translatedText": ""
      },
      {
        "translatedText": "Lidl is doing well because its stores do not have fresh fish or meat counters."
      },
      {
        "translatedText": ""
      },
      {
        "translatedText": "Lidl stores also do not have salad bars, where food can spoil more easily."
      },
      {
        "translatedText": ""
      },
      {
        "translatedText": "S Group's sales also performed well."
      },
      {
        "translatedText": ""
      },
      {
        "translatedText": "In Prismas and S-markets, there were problems in only 2% of inspections."
      },
      {
        "translatedText": ""
      },
      {
        "translatedText": "## K-Group"
      },
      {
        "translatedText": ""
      },
      {
        "translatedText": "The most problems were in the K-Group stores."
      },
      {
        "translatedText": ""
      },
      {
        "translatedText": "There were errors or deficiencies in 7% of inspections in K-Group stores."
      },
      {
        "translatedText": ""
      },
      {
        "translatedText": "There were often problems with food temperatures and cleanliness."
      },
      {
        "translatedText": ""
      },
      {
        "translatedText": "Large K-Citymarkets in particular received poor ratings."
      },
      {
        "translatedText": ""
      },
      {
        "translatedText": "Health inspection data also shows that the K-Group's results deteriorated over the course of three years."
      },
      {
        "translatedText": ""
      },
      {
        "translatedText": "![A fishmonger's hand lifts salmon fillets at the fish counter. ](https://img.img-cdn.yle.fi/crop_extract,w_8256,h_4644,x_0,y_0/crop_fill,w_767,h_431,ar_16:9,dpr_1/f_auto/39-16589396a2a7294c32dc/1781167222)"
      },
      {
        "translatedText": ""
      },
      {
        "translatedText": "Open image viewer"
      },
      {
        "translatedText": ""
      },
      {
        "translatedText": "Fish and meat spoil easily. That's why it's important to keep them really cold at all times. Photo: Johanna Erjonsalo / Yle"
      },
      {
        "translatedText": ""
      },
      {
        "translatedText": "## Reasons for differences"
      },
      {
        "translatedText": ""
      },
      {
        "translatedText": "Experts say that the big differences are due to how retail chains are managed."
      },
      {
        "translatedText": ""
      },
      {
        "translatedText": "At Lidl and the S Group, all stores have common and strict rules."
      },
      {
        "translatedText": ""
      },
      {
        "translatedText": "The situation is different in the K-Group."
      },
      {
        "translatedText": ""
      },
      {
        "translatedText": "Every K-retailer is an entrepreneur who runs their own store."
      },
      {
        "translatedText": ""
      },
      {
        "translatedText": "That is why the differences between different K-stores are large."
      },
      {
        "translatedText": ""
      },
      {
        "translatedText": "## Cold chain"
      },
      {
        "translatedText": ""
      },
      {
        "translatedText": "Proper food storage and cleanliness are important for human health."
      },
      {
        "translatedText": ""
      },
      {
        "translatedText": "For example, milk, meat and fish must always be kept cold."
      },
      {
        "translatedText": ""
      },
      {
        "translatedText": "This is called the cold chain, meaning that the products remain cold at all times."
      },
      {
        "translatedText": ""
      },
      {
        "translatedText": "If the store's refrigerated shelf is too warm or the premises are dirty, food will start to spoil."
      },
      {
        "translatedText": ""
      },
      {
        "translatedText": "Dangerous bacteria begin to grow rapidly if the temperature is above +6 degrees."
      },
      {
        "translatedText": ""
      },
      {
        "translatedText": "Bacteria can cause food poisoning in humans."
      },
      {
        "translatedText": ""
      },
      {
        "translatedText": "![A customer's hand takes a cold meat package from the refrigerated shelf. ](https://img.img-cdn.yle.fi/crop_extract,w_8088,h_4549,x_0,y_268/crop_fill,w_767,h_431,ar_16:9,dpr_1/f_auto/39-16589416a2a7298d0ec8/1781167239)"
      },
      {
        "translatedText": ""
      },
      {
        "translatedText": "Open image viewer"
      },
      {
        "translatedText": ""
      },
      {
        "translatedText": "Packaged cold cuts must also be kept cold at all times. Inspections found shops where cold cuts were kept too warm. Photo: Johanna Erjonsalo / Yle"
      },
      {
        "translatedText": ""
      },
      {
        "translatedText": "## Repetition"
      },
      {
        "translatedText": ""
      },
      {
        "translatedText": "The topic of this week's news was food safety."
      },
      {
        "translatedText": ""
      },
      {
        "translatedText": "Let's repeat the most important things."
      },
      {
        "translatedText": ""
      },
      {
        "translatedText": "Yle examined information on health inspections of grocery stores."
      },
      {
        "translatedText": ""
      },
      {
        "translatedText": "Lidl and S Group take good care of the cleanliness and temperature of the food. K Group stores had the most problems."
      },
      {
        "translatedText": ""
      },
      {
        "translatedText": "Keeping food refrigerated is important to prevent people from getting food poisoning."
      },
      {
        "translatedText": ""
      },
      {
        "translatedText": "This was the news of the week in plain Finnish. See you again, bye!"
      }
    ]
  }
}
