{
  "data": {
    "translations": [
      {
        "translatedText": "## Irratia \\| Albiste garbiak \\| 2023ko azaroaren 2a osteguna"
      },
      {
        "translatedText": ""
      },
      {
        "translatedText": "Enpresen arazoak. Alderdien ospea. Webguneen aurkako erasoa. Soldaduen agerpena. Eguraldia."
      },
      {
        "translatedText": ""
      },
      {
        "translatedText": "### Enpresen arazoak"
      },
      {
        "translatedText": ""
      },
      {
        "translatedText": "![Metalgintzako enpresa askok arazoak dituzte. Argazkia: Jukka Eskanen / Yle](https://images.cdn.yle.fi/image/upload/c_crop,h_2268,w_4031,x_0,y_410/ar_1.7777777777777777,c_fill,g_faces,h_675,/0_p1_201,/0_p1201 q_auto:eco/f_auto/fl_lossy/v1698216498/39-11907536538b9d499762)"
      },
      {
        "translatedText": ""
      },
      {
        "translatedText": "Finlandiako teknologia-enpresa askok arazo handiak dituzte. Finlandiako enpresen atzerriko bezeroek ez dute produktu nahikorik erosten. Horregatik, enpresek irabazi gutxiegi lortzen dute."
      },
      {
        "translatedText": ""
      },
      {
        "translatedText": "Enpresa teknologiko batzuek langileak murrizten ari direla esan dute jada. Adibidez, Nokia, Fiskars eta Vaisala langileak murrizten ari dira."
      },
      {
        "translatedText": ""
      },
      {
        "translatedText": "Makina-industriako eta metal-industriako enpresek bereziki arazoak dituzte momentu honetan."
      },
      {
        "translatedText": ""
      },
      {
        "translatedText": "Albiste txarra da Finlandiarentzat. Makinen industria eta metal industriako enpresak garrantzitsuak dira Finlandiako ekonomiarako."
      },
      {
        "translatedText": ""
      },
      {
        "translatedText": "Enpresen atzerriko bezeroak laster Finlandiako produktu gehiago erosten hasten ez badira, langabezia areagotu daiteke."
      },
      {
        "translatedText": ""
      },
      {
        "translatedText": "### Alderdien ospea"
      },
      {
        "translatedText": ""
      },
      {
        "translatedText": "![Antti Lindtman SDPko presidentea da. Argazkia: Silja Viitala / Yle](https://images.cdn.yle.fi/image/upload/c_crop,h_2241,w_3984,x_0,y_0/ar_1.7777777777777777,c_fill,g_faces,h_675,w_1200./0,y_1 q_auto:eco/f_auto/fl_lossy/v1696930784/39-118400565251b6be058f)"
      },
      {
        "translatedText": ""
      },
      {
        "translatedText": "SDP Finlandiako alderdirik ezagunena da orain, Yleren inkesta berriaren arabera. SDPren ospea asko igo zen urrian."
      },
      {
        "translatedText": ""
      },
      {
        "translatedText": "Finlandiarren ehuneko 24k SDP onartzen dute orain."
      },
      {
        "translatedText": ""
      },
      {
        "translatedText": "Legebiltzarrerako hauteskundeetan, Koomum izan zen alderdirik handiena, baina bere ospea gutxitu egin da. Koalizioa bigarren alderdirik ezagunena da orain."
      },
      {
        "translatedText": ""
      },
      {
        "translatedText": "Gaur egun finlandiarren %20 inguruk onartzen dute koalizioa."
      },
      {
        "translatedText": ""
      },
      {
        "translatedText": "Oinarrizko finlandiarren ospea ez zen asko aldatu urrian. Hirugarren festarik ezagunena da."
      },
      {
        "translatedText": ""
      },
      {
        "translatedText": "SDPren laguntza handitu egin daiteke gobernuak langabeziaren segurtasuna ahultzeko asmoa duelako, adibidez. SDPk gobernuaren plan asko kritikatu ditu."
      },
      {
        "translatedText": ""
      },
      {
        "translatedText": "### Webguneen aurkako erasoa"
      },
      {
        "translatedText": ""
      },
      {
        "translatedText": "![Suomen Bank eraikina Helsinkiko erdigunean. Argazkia: Matti Myller / Yle ](https://images.cdn.yle.fi/image/upload/c_crop,h_1391,w_2472,x_0,y_112/ar_1.7777777777777777,c_fill,g_faces,h_670/0_r1201. q_auto:eco/f_auto/fl_lossy/v1587997073/39-6686595ea6e8fc70cab)"
      },
      {
        "translatedText": ""
      },
      {
        "translatedText": "Errusiaren aldeko hacker-ek Finlandiako Bankuaren webgunea eraso zuten ostegunean. Webguneak ez zuen normal funtzionatzen."
      },
      {
        "translatedText": ""
      },
      {
        "translatedText": "Erasoa zela eta, Finlandiako Bankuak atzerriko webguneen erabilera blokeatu zuen."
      },
      {
        "translatedText": ""
      },
      {
        "translatedText": "Asteazkenean, hackerrek zerga administrazioaren webguneari eraso zioten."
      },
      {
        "translatedText": ""
      },
      {
        "translatedText": "Errusiaren aldeko hackerrek esan dute bi erasoak egin dituztela."
      },
      {
        "translatedText": ""
      },
      {
        "translatedText": "Finlandiako webguneen aurkako erasoak areagotu egin dira iaz Errusiak Ukrainari eraso zionetik."
      },
      {
        "translatedText": ""
      },
      {
        "translatedText": "### Soldaduen agerpena"
      },
      {
        "translatedText": ""
      },
      {
        "translatedText": "![Gizonezko soldaduek ez dute ile luzerik izan behar. Argazkia: Linus Westerlund](https://images.cdn.yle.fi/image/upload/c_crop,h_3375,w_6000,x_0,y_522/ar_1.7777777777777777,c_fill,g_faces,h_675,/0q_p1201,/0q_p1201./0_auto eco/f_auto/fl_lossy/v1688460639/39-113784464a3db01e8a65)"
      },
      {
        "translatedText": ""
      },
      {
        "translatedText": "Armadaren itxura baldintzak aldatu nahi dituzte erakunde militarrek."
      },
      {
        "translatedText": ""
      },
      {
        "translatedText": "Etorkizunean armadako soldaduek bizarra eta bibotea edukitzea espero dute erakunde militarrek."
      },
      {
        "translatedText": ""
      },
      {
        "translatedText": "Armadako buruzagitzak dio armadaren itxura baldintzak etorkizunean alda daitezkeela."
      },
      {
        "translatedText": ""
      },
      {
        "translatedText": "Gaur egun, gizonek ile motza izan behar dute armadan. Bizarra eta bibotea moztu behar dira. Emakume soldaduek ile luzea izan dezakete,"
      },
      {
        "translatedText": ""
      },
      {
        "translatedText": "### Eguraldia"
      },
      {
        "translatedText": ""
      },
      {
        "translatedText": "![ Argazkia: Yle](https://images.cdn.yle.fi/image/upload/c_crop,h_1080,w_1919,x_0,y_0/ar_1.777777777777777,c_fill,g_faces,h_675,w_rq_auto/0dp_1201/0dp :eco/f_auto/fl_lossy/v1698940434/39-11951316543c5fbc620f)"
      },
      {
        "translatedText": ""
      },
      {
        "translatedText": "Ostiralean euri pixka bat edo elurra egin dezake. Ostiral arratsaldean euri gehiago egin dezake hegoaldean. Tenperatura +7 eta -12 gradu artekoa da. Iparraldean hotzena da."
      }
    ]
  }
}
